<?xml version="1.0" encoding="UTF-8"?>
<Configuration status="WARN">
    <properties>
        <property name="log_path">D:/work Space/log</property>
        <property name="file_name">file.log</property>
        <property name="root_level">error</property>
    </properties>

    <Appenders>
        <!--console :控制台输出的配置-->
        <Console name="Console" target="SYSTEM_OUT">
            <PatternLayout pattern="%d{HH:mm:ss.SSS} [%t] %-5level %logger{36} - %msg%n"/>
        </Console>

        <!--File :同步输出日志到本地文件 append:是否追加写-->
        <File name="log" fileName="${logFilePath}/${logFileName}" append="false">
            <PatternLayout pattern="%d{HH:mm:ss.SSS} %-5level %class{36} %L %M - %msg%xEx%n"/>
        </File>
        <!--RollingFile：日志滚动策略-->
        <RollingFile name="RollingFileInfo" fileName="${sys:user.home}/logs/info.log"
                     filePattern="${sys:user.home}/logs/$${date:yyyy-MM}/info-%d{yyyy-MM-dd}-%i.log">
            <!--ThresholdFilter :日志输出过滤-->
            <!--level="info" :日志级别,onMatch="ACCEPT" :级别在info之上则接受,onMismatch="DENY" :级别在info之下则拒绝-->
            <ThresholdFilter level="info" onMatch="ACCEPT" onMismatch="DENY"/>
            <PatternLayout pattern="[%d{HH:mm:ss:SSS}] [%p] - %l - %m%n"/>
            <!-- Policies :日志滚动策略-->
            <Policies>
                <!-- TimeBasedTriggeringPolicy :时间滚动策略,默认0点小时产生新的文件,interval="6" : 自定义文件滚动时间间隔,每隔6小时产生新文件, modulate="true" : 产生文件是否以0点偏移时间,即6点,12点,18点,0点-->
                <TimeBasedTriggeringPolicy interval="6" modulate="true"/>
                <!-- SizeBasedTriggeringPolicy :文件大小滚动策略-->
                <SizeBasedTriggeringPolicy size="100 MB"/>
            </Policies>
            <!-- DefaultRolloverStrategy属性如不设置，则默认为最多同一文件夹下7个文件，这里设置了20 -->
            <DefaultRolloverStrategy max="20"/>
        </RollingFile>
    </Appenders>

    <Loggers>
        <Root level="${log_path}">
            <AppenderRef ref="Console"/>
        </Root>
        <!--配置Mybatis Sql语句打印-->
        <logger name="com.yw.demo" level="debug" additivity="false">
            <AppenderRef ref="Console"/>
        </logger>
    </Loggers>
</Configuration>
